deep_rehab_pile/__init__.py
deep_rehab_pile-0.1.2.dist-info/licenses/LICENSE
deep_rehab_pile-0.1.2.dist-info/METADATA
deep_rehab_pile-0.1.2.dist-info/WHEEL
deep_rehab_pile-0.1.2.dist-info/top_level.txt
deep_rehab_pile-0.1.2.dist-info/RECORD
